source/__init__.py
source/linux.py
source/main.py
source/windows.py
access_watch-1.0.dist-info/LICENSE
access_watch-1.0.dist-info/METADATA
access_watch-1.0.dist-info/WHEEL
access_watch-1.0.dist-info/top_level.txt
access_watch-1.0.dist-info/RECORD
