Metadata-Version: 2.1
Name: access-watch
Version: 1.0
Summary: A tool that retrieves and displays file or directory access information In Linux and Windows
License-File: LICENSE
